geoso/__init__.py
geoso/clean_text.py
geoso/cli.py
geoso/geoso.py
geoso/postgres.py
geoso/twitter_data_retrieval.py
geoso/twitter_reader_writer.py
geoso/utils.py
geoso-0.0.11.dist-info/LICENSE
geoso-0.0.11.dist-info/METADATA
geoso-0.0.11.dist-info/WHEEL
geoso-0.0.11.dist-info/dependency_links.txt
geoso-0.0.11.dist-info/entry_points.txt
geoso-0.0.11.dist-info/top_level.txt
geoso-0.0.11.dist-info/RECORD
