Metadata-Version: 2.1
Name: geoso
Version: 0.0.11
Summary: A Python package for spatio-temporal analysis of social media contents
Home-page: https://github.com/MahdiFarnaghi/geoso
Author: Mahdi Farnaghi
Author-email: mahdi.farnaghi@outlook.com
License: MIT license
Keywords: geoso
Classifier: Development Status :: 2 - Pre-Alpha
Classifier: Intended Audience :: Developers
Classifier: License :: OSI Approved :: MIT License
Classifier: Natural Language :: English
Classifier: Programming Language :: Python :: 3
Classifier: Programming Language :: Python :: 3.5
Classifier: Programming Language :: Python :: 3.6
Classifier: Programming Language :: Python :: 3.7
Classifier: Programming Language :: Python :: 3.8
Requires-Python: >=3.5
License-File: LICENSE
Requires-Dist: Click
Requires-Dist: numpy
Requires-Dist: pandas
Requires-Dist: colorama
Requires-Dist: termcolor
Requires-Dist: python-dotenv
Requires-Dist: tweepy (==3.9.0)
Requires-Dist: geoalchemy2 (==0.8.4)
Requires-Dist: sqlalchemy (==1.4.23)
Requires-Dist: sqlalchemy-utils (==0.37.8)
Requires-Dist: psycopg2-binary
Requires-Dist: pycountry (==20.7.3)
Requires-Dist: spacy
Requires-Dist: pymorphy2 (==0.8)
Requires-Dist: pymorphy2-dicts
Requires-Dist: descartes (==1.1.0)
Requires-Dist: tika (==1.24)
